{
    "metadados": {
        "projeto": "ECODATA",
        "nome_serie": "yahoo_euro_real",
        "nome_exibicao": "EURO REAL",
        "codigo": null,
        "fonte": "yahoo",
        "grupo": "mercado_financeiro",
        "frequencia": "mensal",
        "primeira_data": "2021-07-31",
        "ultima_data": "2026-07-31",
        "observacoes": 61,
        "data_geracao": "2026-07-23 11:52:02",
        "arquivo_origem": "data/final/series/yahoo_euro_real.csv",
        "unidade": null,
        "descricao": null,
        "ajuste_sazonal": null,
        "nota_metodologica": "Indicadores calculados automaticamente a partir da série histórica disponível. As classificações de tendência são descritivas e não representam previsões."
    },
    "indicadores": {
        "ultima_data": "2026-07-31",
        "ultimo_valor": 5.7601,
        "variacao_absoluta_1_mes": -0.15706,
        "variacao_absoluta_3_meses": -0.098131,
        "variacao_absoluta_12_meses": -0.605272,
        "variacao_1_mes_pct": -2.654314,
        "variacao_3_meses_pct": -1.675096,
        "variacao_6_meses_pct": -7.147189,
        "variacao_12_meses_pct": -9.508824,
        "media_movel_3": 5.853204,
        "media_movel_6": 5.917085,
        "media_movel_12": 6.093187,
        "desvio_media_movel_3_pct": -1.590656,
        "desvio_media_movel_12_pct": -5.46654,
        "volatilidade_12_meses": 1.911237,
        "media_historica": 5.817075,
        "mediana_historica": 5.882353,
        "desvio_padrao_historico": 0.438688,
        "minimo_historico": 5.1176,
        "data_minimo_historico": "2022-05-31",
        "maximo_historico": 6.593,
        "data_maximo_historico": "2021-10-31",
        "minimo_ultimos_12_meses": 5.7601,
        "maximo_ultimos_12_meses": 6.426735,
        "percentil_historico": 45.901639,
        "sequencia_atual": {
            "direcao": "queda",
            "periodos": 1
        },
        "aceleracao_variacao_mensal": -3.246033,
        "classificacao_aceleracao": "negativa",
        "tendencia_recente": "queda"
    },
    "serie": [
        {
            "data": "2021-07-31",
            "valor": 6.0387,
            "variacao_absoluta_1_mes": null,
            "variacao_absoluta_3_meses": null,
            "variacao_absoluta_12_meses": null,
            "variacao_1_mes_pct": null,
            "variacao_3_meses_pct": null,
            "variacao_6_meses_pct": null,
            "variacao_12_meses_pct": null,
            "media_movel_3": null,
            "media_movel_6": null,
            "media_movel_12": null,
            "desvio_media_movel_3_pct": null,
            "desvio_media_movel_12_pct": null,
            "volatilidade_12_meses": null,
            "minimo_movel_12_meses": 6.0387,
            "maximo_movel_12_meses": 6.0387,
            "aceleracao_variacao_mensal": null
        },
        {
            "data": "2021-08-31",
            "valor": 6.1119,
            "variacao_absoluta_1_mes": 0.0732,
            "variacao_absoluta_3_meses": null,
            "variacao_absoluta_12_meses": null,
            "variacao_1_mes_pct": 1.212181,
            "variacao_3_meses_pct": null,
            "variacao_6_meses_pct": null,
            "variacao_12_meses_pct": null,
            "media_movel_3": null,
            "media_movel_6": null,
            "media_movel_12": null,
            "desvio_media_movel_3_pct": null,
            "desvio_media_movel_12_pct": null,
            "volatilidade_12_meses": null,
            "minimo_movel_12_meses": 6.0387,
            "maximo_movel_12_meses": 6.1119,
            "aceleracao_variacao_mensal": null
        },
        {
            "data": "2021-09-30",
            "valor": 6.2785,
            "variacao_absoluta_1_mes": 0.1666,
            "variacao_absoluta_3_meses": null,
            "variacao_absoluta_12_meses": null,
            "variacao_1_mes_pct": 2.72583,
            "variacao_3_meses_pct": null,
            "variacao_6_meses_pct": null,
            "variacao_12_meses_pct": null,
            "media_movel_3": 6.143033,
            "media_movel_6": null,
            "media_movel_12": null,
            "desvio_media_movel_3_pct": 2.205208,
            "desvio_media_movel_12_pct": null,
            "volatilidade_12_meses": null,
            "minimo_movel_12_meses": 6.0387,
            "maximo_movel_12_meses": 6.2785,
            "aceleracao_variacao_mensal": 1.513649
        },
        {
            "data": "2021-10-31",
            "valor": 6.593,
            "variacao_absoluta_1_mes": 0.3145,
            "variacao_absoluta_3_meses": 0.5543,
            "variacao_absoluta_12_meses": null,
            "variacao_1_mes_pct": 5.009158,
            "variacao_3_meses_pct": 9.179128,
            "variacao_6_meses_pct": null,
            "variacao_12_meses_pct": null,
            "media_movel_3": 6.3278,
            "media_movel_6": null,
            "media_movel_12": null,
            "desvio_media_movel_3_pct": 4.19103,
            "desvio_media_movel_12_pct": null,
            "volatilidade_12_meses": null,
            "minimo_movel_12_meses": 6.0387,
            "maximo_movel_12_meses": 6.593,
            "aceleracao_variacao_mensal": 2.283328
        },
        {
            "data": "2021-11-30",
            "valor": 6.3223,
            "variacao_absoluta_1_mes": -0.2707,
            "variacao_absoluta_3_meses": 0.2104,
            "variacao_absoluta_12_meses": null,
            "variacao_1_mes_pct": -4.10587,
            "variacao_3_meses_pct": 3.442465,
            "variacao_6_meses_pct": null,
            "variacao_12_meses_pct": null,
            "media_movel_3": 6.397933,
            "media_movel_6": null,
            "media_movel_12": null,
            "desvio_media_movel_3_pct": -1.182153,
            "desvio_media_movel_12_pct": null,
            "volatilidade_12_meses": null,
            "minimo_movel_12_meses": 6.0387,
            "maximo_movel_12_meses": 6.593,
            "aceleracao_variacao_mensal": -9.115028
        },
        {
            "data": "2021-12-31",
            "valor": 6.3049,
            "variacao_absoluta_1_mes": -0.0174,
            "variacao_absoluta_3_meses": 0.0264,
            "variacao_absoluta_12_meses": null,
            "variacao_1_mes_pct": -0.275216,
            "variacao_3_meses_pct": 0.420483,
            "variacao_6_meses_pct": null,
            "variacao_12_meses_pct": null,
            "media_movel_3": 6.406733,
            "media_movel_6": 6.274883,
            "media_movel_12": null,
            "desvio_media_movel_3_pct": -1.589474,
            "desvio_media_movel_12_pct": null,
            "volatilidade_12_meses": null,
            "minimo_movel_12_meses": 6.0387,
            "maximo_movel_12_meses": 6.593,
            "aceleracao_variacao_mensal": 3.830654
        },
        {
            "data": "2022-01-31",
            "valor": 5.9782,
            "variacao_absoluta_1_mes": -0.3267,
            "variacao_absoluta_3_meses": -0.6148,
            "variacao_absoluta_12_meses": null,
            "variacao_1_mes_pct": -5.181684,
            "variacao_3_meses_pct": -9.325042,
            "variacao_6_meses_pct": -1.001871,
            "variacao_12_meses_pct": null,
            "media_movel_3": 6.2018,
            "media_movel_6": 6.2648,
            "media_movel_12": null,
            "desvio_media_movel_3_pct": -3.605405,
            "desvio_media_movel_12_pct": null,
            "volatilidade_12_meses": null,
            "minimo_movel_12_meses": 5.9782,
            "maximo_movel_12_meses": 6.593,
            "aceleracao_variacao_mensal": -4.906468
        },
        {
            "data": "2022-02-28",
            "valor": 5.814,
            "variacao_absoluta_1_mes": -0.1642,
            "variacao_absoluta_3_meses": -0.5083,
            "variacao_absoluta_12_meses": null,
            "variacao_1_mes_pct": -2.746646,
            "variacao_3_meses_pct": -8.039796,
            "variacao_6_meses_pct": -4.874098,
            "variacao_12_meses_pct": null,
            "media_movel_3": 6.032367,
            "media_movel_6": 6.21515,
            "media_movel_12": null,
            "desvio_media_movel_3_pct": -3.619917,
            "desvio_media_movel_12_pct": null,
            "volatilidade_12_meses": null,
            "minimo_movel_12_meses": 5.814,
            "maximo_movel_12_meses": 6.593,
            "aceleracao_variacao_mensal": 2.435038
        },
        {
            "data": "2022-03-31",
            "valor": 5.3198,
            "variacao_absoluta_1_mes": -0.4942,
            "variacao_absoluta_3_meses": -0.9851,
            "variacao_absoluta_12_meses": null,
            "variacao_1_mes_pct": -8.500172,
            "variacao_3_meses_pct": -15.624356,
            "variacao_6_meses_pct": -15.269571,
            "variacao_12_meses_pct": null,
            "media_movel_3": 5.704,
            "media_movel_6": 6.055367,
            "media_movel_12": null,
            "desvio_media_movel_3_pct": -6.735624,
            "desvio_media_movel_12_pct": null,
            "volatilidade_12_meses": null,
            "minimo_movel_12_meses": 5.3198,
            "maximo_movel_12_meses": 6.593,
            "aceleracao_variacao_mensal": -5.753526
        },
        {
            "data": "2022-04-30",
            "valor": 5.1837,
            "variacao_absoluta_1_mes": -0.1361,
            "variacao_absoluta_3_meses": -0.7945,
            "variacao_absoluta_12_meses": null,
            "variacao_1_mes_pct": -2.558367,
            "variacao_3_meses_pct": -13.289953,
            "variacao_6_meses_pct": -21.375702,
            "variacao_12_meses_pct": null,
            "media_movel_3": 5.439167,
            "media_movel_6": 5.820483,
            "media_movel_12": null,
            "desvio_media_movel_3_pct": -4.696798,
            "desvio_media_movel_12_pct": null,
            "volatilidade_12_meses": null,
            "minimo_movel_12_meses": 5.1837,
            "maximo_movel_12_meses": 6.593,
            "aceleracao_variacao_mensal": 5.941805
        },
        {
            "data": "2022-05-31",
            "valor": 5.1176,
            "variacao_absoluta_1_mes": -0.0661,
            "variacao_absoluta_3_meses": -0.6964,
            "variacao_absoluta_12_meses": null,
            "variacao_1_mes_pct": -1.275151,
            "variacao_3_meses_pct": -11.977984,
            "variacao_6_meses_pct": -19.054774,
            "variacao_12_meses_pct": null,
            "media_movel_3": 5.207033,
            "media_movel_6": 5.6197,
            "media_movel_12": null,
            "desvio_media_movel_3_pct": -1.717549,
            "desvio_media_movel_12_pct": null,
            "volatilidade_12_meses": null,
            "minimo_movel_12_meses": 5.1176,
            "maximo_movel_12_meses": 6.593,
            "aceleracao_variacao_mensal": 1.283216
        },
        {
            "data": "2022-06-30",
            "valor": 5.4098,
            "variacao_absoluta_1_mes": 0.2922,
            "variacao_absoluta_3_meses": 0.09,
            "variacao_absoluta_12_meses": null,
            "variacao_1_mes_pct": 5.709708,
            "variacao_3_meses_pct": 1.691793,
            "variacao_6_meses_pct": -14.196894,
            "variacao_12_meses_pct": null,
            "media_movel_3": 5.237033,
            "media_movel_6": 5.470517,
            "media_movel_12": 5.8727,
            "desvio_media_movel_3_pct": 3.298942,
            "desvio_media_movel_12_pct": -7.882235,
            "volatilidade_12_meses": null,
            "minimo_movel_12_meses": 5.1176,
            "maximo_movel_12_meses": 6.593,
            "aceleracao_variacao_mensal": 6.984859
        },
        {
            "data": "2022-07-31",
            "valor": 5.2797,
            "variacao_absoluta_1_mes": -0.1301,
            "variacao_absoluta_3_meses": 0.096,
            "variacao_absoluta_12_meses": -0.759,
            "variacao_1_mes_pct": -2.404895,
            "variacao_3_meses_pct": 1.851959,
            "variacao_6_meses_pct": -11.684119,
            "variacao_12_meses_pct": -12.56893,
            "media_movel_3": 5.269033,
            "media_movel_6": 5.3541,
            "media_movel_12": 5.80945,
            "desvio_media_movel_3_pct": 0.202441,
            "desvio_media_movel_12_pct": -9.118763,
            "volatilidade_12_meses": 4.170595,
            "minimo_movel_12_meses": 5.1176,
            "maximo_movel_12_meses": 6.593,
            "aceleracao_variacao_mensal": -8.114602
        },
        {
            "data": "2022-08-31",
            "valor": 5.1318,
            "variacao_absoluta_1_mes": -0.1479,
            "variacao_absoluta_3_meses": 0.0142,
            "variacao_absoluta_12_meses": -0.9801,
            "variacao_1_mes_pct": -2.801296,
            "variacao_3_meses_pct": 0.277474,
            "variacao_6_meses_pct": -11.733746,
            "variacao_12_meses_pct": -16.03593,
            "media_movel_3": 5.273767,
            "media_movel_6": 5.2404,
            "media_movel_12": 5.727775,
            "desvio_media_movel_3_pct": -2.691941,
            "desvio_media_movel_12_pct": -10.405,
            "volatilidade_12_meses": 4.134989,
            "minimo_movel_12_meses": 5.1176,
            "maximo_movel_12_meses": 6.593,
            "aceleracao_variacao_mensal": -0.396401
        },
        {
            "data": "2022-09-30",
            "valor": 5.3031,
            "variacao_absoluta_1_mes": 0.1713,
            "variacao_absoluta_3_meses": -0.1067,
            "variacao_absoluta_12_meses": -0.9754,
            "variacao_1_mes_pct": 3.33801,
            "variacao_3_meses_pct": -1.972346,
            "variacao_6_meses_pct": -0.313922,
            "variacao_12_meses_pct": -15.535558,
            "media_movel_3": 5.2382,
            "media_movel_6": 5.237617,
            "media_movel_12": 5.646492,
            "desvio_media_movel_3_pct": 1.238975,
            "desvio_media_movel_12_pct": -6.081505,
            "volatilidade_12_meses": 4.193438,
            "minimo_movel_12_meses": 5.1176,
            "maximo_movel_12_meses": 6.593,
            "aceleracao_variacao_mensal": 6.139306
        },
        {
            "data": "2022-10-31",
            "valor": 5.2737,
            "variacao_absoluta_1_mes": -0.0294,
            "variacao_absoluta_3_meses": -0.006,
            "variacao_absoluta_12_meses": -1.3193,
            "variacao_1_mes_pct": -0.554393,
            "variacao_3_meses_pct": -0.113643,
            "variacao_6_meses_pct": 1.736212,
            "variacao_12_meses_pct": -20.010617,
            "media_movel_3": 5.2362,
            "media_movel_6": 5.252617,
            "media_movel_12": 5.53655,
            "desvio_media_movel_3_pct": 0.716168,
            "desvio_media_movel_12_pct": -4.747541,
            "volatilidade_12_meses": 3.710265,
            "minimo_movel_12_meses": 5.1176,
            "maximo_movel_12_meses": 6.3223,
            "aceleracao_variacao_mensal": -3.892403
        },
        {
            "data": "2022-11-30",
            "valor": 5.4362,
            "variacao_absoluta_1_mes": 0.1625,
            "variacao_absoluta_3_meses": 0.3044,
            "variacao_absoluta_12_meses": -0.8861,
            "variacao_1_mes_pct": 3.081328,
            "variacao_3_meses_pct": 5.931642,
            "variacao_6_meses_pct": 6.225574,
            "variacao_12_meses_pct": -14.015469,
            "media_movel_3": 5.337667,
            "media_movel_6": 5.305717,
            "media_movel_12": 5.462708,
            "desvio_media_movel_3_pct": 1.846,
            "desvio_media_movel_12_pct": -0.48526,
            "volatilidade_12_meses": 3.876973,
            "minimo_movel_12_meses": 5.1176,
            "maximo_movel_12_meses": 6.3049,
            "aceleracao_variacao_mensal": 3.635721
        },
        {
            "data": "2022-12-31",
            "valor": 5.633,
            "variacao_absoluta_1_mes": 0.1968,
            "variacao_absoluta_3_meses": 0.3299,
            "variacao_absoluta_12_meses": -0.6719,
            "variacao_1_mes_pct": 3.620176,
            "variacao_3_meses_pct": 6.22089,
            "variacao_6_meses_pct": 4.125846,
            "variacao_12_meses_pct": -10.656791,
            "media_movel_3": 5.447633,
            "media_movel_6": 5.342917,
            "media_movel_12": 5.406717,
            "desvio_media_movel_3_pct": 3.402701,
            "desvio_media_movel_12_pct": 4.185226,
            "volatilidade_12_meses": 4.115429,
            "minimo_movel_12_meses": 5.1176,
            "maximo_movel_12_meses": 5.9782,
            "aceleracao_variacao_mensal": 0.538848
        },
        {
            "data": "2023-01-31",
            "valor": 5.5471,
            "variacao_absoluta_1_mes": -0.0859,
            "variacao_absoluta_3_meses": 0.2734,
            "variacao_absoluta_12_meses": -0.4311,
            "variacao_1_mes_pct": -1.524942,
            "variacao_3_meses_pct": 5.184216,
            "variacao_6_meses_pct": 5.064682,
            "variacao_12_meses_pct": -7.211201,
            "media_movel_3": 5.538767,
            "media_movel_6": 5.387483,
            "media_movel_12": 5.370792,
            "desvio_media_movel_3_pct": 0.150455,
            "desvio_media_movel_12_pct": 3.282725,
            "volatilidade_12_meses": 3.895531,
            "minimo_movel_12_meses": 5.1176,
            "maximo_movel_12_meses": 5.814,
            "aceleracao_variacao_mensal": -5.145118
        },
        {
            "data": "2023-02-28",
            "valor": 5.514,
            "variacao_absoluta_1_mes": -0.0331,
            "variacao_absoluta_3_meses": 0.0778,
            "variacao_absoluta_12_meses": -0.3,
            "variacao_1_mes_pct": -0.596708,
            "variacao_3_meses_pct": 1.431147,
            "variacao_6_meses_pct": 7.447679,
            "variacao_12_meses_pct": -5.159959,
            "media_movel_3": 5.5647,
            "media_movel_6": 5.451183,
            "media_movel_12": 5.345792,
            "desvio_media_movel_3_pct": -0.9111,
            "desvio_media_movel_12_pct": 3.146556,
            "volatilidade_12_meses": 3.834349,
            "minimo_movel_12_meses": 5.1176,
            "maximo_movel_12_meses": 5.633,
            "aceleracao_variacao_mensal": 0.928234
        },
        {
            "data": "2023-03-31",
            "valor": 5.5518,
            "variacao_absoluta_1_mes": 0.0378,
            "variacao_absoluta_3_meses": -0.0812,
            "variacao_absoluta_12_meses": 0.232,
            "variacao_1_mes_pct": 0.685528,
            "variacao_3_meses_pct": -1.441505,
            "variacao_6_meses_pct": 4.68971,
            "variacao_12_meses_pct": 4.361066,
            "media_movel_3": 5.537633,
            "media_movel_6": 5.492633,
            "media_movel_12": 5.365125,
            "desvio_media_movel_3_pct": 0.255825,
            "desvio_media_movel_12_pct": 3.479416,
            "volatilidade_12_meses": 2.856387,
            "minimo_movel_12_meses": 5.1176,
            "maximo_movel_12_meses": 5.633,
            "aceleracao_variacao_mensal": 1.282236
        },
        {
            "data": "2023-04-30",
            "valor": 5.4883,
            "variacao_absoluta_1_mes": -0.0635,
            "variacao_absoluta_3_meses": -0.0588,
            "variacao_absoluta_12_meses": 0.3046,
            "variacao_1_mes_pct": -1.143773,
            "variacao_3_meses_pct": -1.060013,
            "variacao_6_meses_pct": 4.069249,
            "variacao_12_meses_pct": 5.876112,
            "media_movel_3": 5.518033,
            "media_movel_6": 5.5284,
            "media_movel_12": 5.390508,
            "desvio_media_movel_3_pct": -0.538839,
            "desvio_media_movel_12_pct": 1.814146,
            "volatilidade_12_meses": 2.750736,
            "minimo_movel_12_meses": 5.1176,
            "maximo_movel_12_meses": 5.633,
            "aceleracao_variacao_mensal": -1.829301
        },
        {
            "data": "2023-05-31",
            "valor": 5.4012,
            "variacao_absoluta_1_mes": -0.0871,
            "variacao_absoluta_3_meses": -0.1128,
            "variacao_absoluta_12_meses": 0.2836,
            "variacao_1_mes_pct": -1.587012,
            "variacao_3_meses_pct": -2.045702,
            "variacao_6_meses_pct": -0.643832,
            "variacao_12_meses_pct": 5.54166,
            "media_movel_3": 5.480433,
            "media_movel_6": 5.522567,
            "media_movel_12": 5.414142,
            "desvio_media_movel_3_pct": -1.445749,
            "desvio_media_movel_12_pct": -0.239035,
            "volatilidade_12_meses": 2.770549,
            "minimo_movel_12_meses": 5.1318,
            "maximo_movel_12_meses": 5.633,
            "aceleracao_variacao_mensal": -0.443239
        },
        {
            "data": "2023-06-30",
            "valor": 5.2739,
            "variacao_absoluta_1_mes": -0.1273,
            "variacao_absoluta_3_meses": -0.2779,
            "variacao_absoluta_12_meses": -0.1359,
            "variacao_1_mes_pct": -2.356884,
            "variacao_3_meses_pct": -5.005584,
            "variacao_6_meses_pct": -6.374933,
            "variacao_12_meses_pct": -2.512108,
            "media_movel_3": 5.3878,
            "media_movel_6": 5.462717,
            "media_movel_12": 5.402817,
            "desvio_media_movel_3_pct": -2.114035,
            "desvio_media_movel_12_pct": -2.386101,
            "volatilidade_12_meses": 2.331483,
            "minimo_movel_12_meses": 5.1318,
            "maximo_movel_12_meses": 5.633,
            "aceleracao_variacao_mensal": -0.769871
        },
        {
            "data": "2023-07-31",
            "valor": 5.1895,
            "variacao_absoluta_1_mes": -0.0844,
            "variacao_absoluta_3_meses": -0.2988,
            "variacao_absoluta_12_meses": -0.0902,
            "variacao_1_mes_pct": -1.600334,
            "variacao_3_meses_pct": -5.444309,
            "variacao_6_meses_pct": -6.446612,
            "variacao_12_meses_pct": -1.70843,
            "media_movel_3": 5.2882,
            "media_movel_6": 5.403117,
            "media_movel_12": 5.3953,
            "desvio_media_movel_3_pct": -1.86642,
            "desvio_media_movel_12_pct": -3.814431,
            "volatilidade_12_meses": 2.272735,
            "minimo_movel_12_meses": 5.1318,
            "maximo_movel_12_meses": 5.633,
            "aceleracao_variacao_mensal": 0.75655
        },
        {
            "data": "2023-08-31",
            "valor": 5.313,
            "variacao_absoluta_1_mes": 0.1235,
            "variacao_absoluta_3_meses": -0.0882,
            "variacao_absoluta_12_meses": 0.1812,
            "variacao_1_mes_pct": 2.379805,
            "variacao_3_meses_pct": -1.63297,
            "variacao_6_meses_pct": -3.645267,
            "variacao_12_meses_pct": 3.530925,
            "media_movel_3": 5.2588,
            "media_movel_6": 5.369617,
            "media_movel_12": 5.4104,
            "desvio_media_movel_3_pct": 1.030653,
            "desvio_media_movel_12_pct": -1.800237,
            "volatilidade_12_meses": 2.20828,
            "minimo_movel_12_meses": 5.1895,
            "maximo_movel_12_meses": 5.633,
            "aceleracao_variacao_mensal": 3.980139
        },
        {
            "data": "2023-09-30",
            "valor": 5.3197,
            "variacao_absoluta_1_mes": 0.0067,
            "variacao_absoluta_3_meses": 0.0458,
            "variacao_absoluta_12_meses": 0.0166,
            "variacao_1_mes_pct": 0.126106,
            "variacao_3_meses_pct": 0.868428,
            "variacao_6_meses_pct": -4.180626,
            "variacao_12_meses_pct": 0.313024,
            "media_movel_3": 5.274067,
            "media_movel_6": 5.330933,
            "media_movel_12": 5.411783,
            "desvio_media_movel_3_pct": 0.86524,
            "desvio_media_movel_12_pct": -1.701534,
            "volatilidade_12_meses": 1.99221,
            "minimo_movel_12_meses": 5.1895,
            "maximo_movel_12_meses": 5.633,
            "aceleracao_variacao_mensal": -2.2537
        },
        {
            "data": "2023-10-31",
            "valor": 5.3537,
            "variacao_absoluta_1_mes": 0.034,
            "variacao_absoluta_3_meses": 0.1642,
            "variacao_absoluta_12_meses": 0.08,
            "variacao_1_mes_pct": 0.639134,
            "variacao_3_meses_pct": 3.164081,
            "variacao_6_meses_pct": -2.45249,
            "variacao_12_meses_pct": 1.516962,
            "media_movel_3": 5.3288,
            "media_movel_6": 5.3085,
            "media_movel_12": 5.41845,
            "desvio_media_movel_3_pct": 0.467272,
            "desvio_media_movel_12_pct": -1.194991,
            "volatilidade_12_meses": 1.989407,
            "minimo_movel_12_meses": 5.1895,
            "maximo_movel_12_meses": 5.633,
            "aceleracao_variacao_mensal": 0.513028
        },
        {
            "data": "2023-11-30",
            "valor": 5.3628,
            "variacao_absoluta_1_mes": 0.0091,
            "variacao_absoluta_3_meses": 0.0498,
            "variacao_absoluta_12_meses": -0.0734,
            "variacao_1_mes_pct": 0.169976,
            "variacao_3_meses_pct": 0.937324,
            "variacao_6_meses_pct": -0.710953,
            "variacao_12_meses_pct": -1.350208,
            "media_movel_3": 5.3454,
            "media_movel_6": 5.3021,
            "media_movel_12": 5.412333,
            "desvio_media_movel_3_pct": 0.325514,
            "desvio_media_movel_12_pct": -0.915194,
            "volatilidade_12_meses": 1.763233,
            "minimo_movel_12_meses": 5.1895,
            "maximo_movel_12_meses": 5.633,
            "aceleracao_variacao_mensal": -0.469158
        },
        {
            "data": "2023-12-31",
            "valor": 5.343,
            "variacao_absoluta_1_mes": -0.0198,
            "variacao_absoluta_3_meses": 0.0233,
            "variacao_absoluta_12_meses": -0.29,
            "variacao_1_mes_pct": -0.36921,
            "variacao_3_meses_pct": 0.437995,
            "variacao_6_meses_pct": 1.310226,
            "variacao_12_meses_pct": -5.148234,
            "media_movel_3": 5.353167,
            "media_movel_6": 5.313617,
            "media_movel_12": 5.388167,
            "desvio_media_movel_3_pct": -0.189919,
            "desvio_media_movel_12_pct": -0.838257,
            "volatilidade_12_meses": 1.318151,
            "minimo_movel_12_meses": 5.1895,
            "maximo_movel_12_meses": 5.5518,
            "aceleracao_variacao_mensal": -0.539186
        },
        {
            "data": "2024-01-31",
            "valor": 5.3604,
            "variacao_absoluta_1_mes": 0.0174,
            "variacao_absoluta_3_meses": 0.0067,
            "variacao_absoluta_12_meses": -0.1867,
            "variacao_1_mes_pct": 0.32566,
            "variacao_3_meses_pct": 0.125147,
            "variacao_6_meses_pct": 3.293188,
            "variacao_12_meses_pct": -3.365723,
            "media_movel_3": 5.3554,
            "media_movel_6": 5.3421,
            "media_movel_12": 5.372608,
            "desvio_media_movel_3_pct": 0.093364,
            "desvio_media_movel_12_pct": -0.227233,
            "volatilidade_12_meses": 1.286473,
            "minimo_movel_12_meses": 5.1895,
            "maximo_movel_12_meses": 5.5518,
            "aceleracao_variacao_mensal": 0.69487
        },
        {
            "data": "2024-02-29",
            "valor": 5.381,
            "variacao_absoluta_1_mes": 0.0206,
            "variacao_absoluta_3_meses": 0.0182,
            "variacao_absoluta_12_meses": -0.133,
            "variacao_1_mes_pct": 0.3843,
            "variacao_3_meses_pct": 0.339375,
            "variacao_6_meses_pct": 1.27988,
            "variacao_12_meses_pct": -2.412042,
            "media_movel_3": 5.361467,
            "media_movel_6": 5.353433,
            "media_movel_12": 5.361525,
            "desvio_media_movel_3_pct": 0.364328,
            "desvio_media_movel_12_pct": 0.363236,
            "volatilidade_12_meses": 1.295469,
            "minimo_movel_12_meses": 5.1895,
            "maximo_movel_12_meses": 5.5518,
            "aceleracao_variacao_mensal": 0.05864
        },
        {
            "data": "2024-03-31",
            "valor": 5.4065,
            "variacao_absoluta_1_mes": 0.0255,
            "variacao_absoluta_3_meses": 0.0635,
            "variacao_absoluta_12_meses": -0.1453,
            "variacao_1_mes_pct": 0.47389,
            "variacao_3_meses_pct": 1.188471,
            "variacao_6_meses_pct": 1.631671,
            "variacao_12_meses_pct": -2.617169,
            "media_movel_3": 5.382633,
            "media_movel_6": 5.3679,
            "media_movel_12": 5.349417,
            "desvio_media_movel_3_pct": 0.443401,
            "desvio_media_movel_12_pct": 1.067095,
            "volatilidade_12_meses": 1.283771,
            "minimo_movel_12_meses": 5.1895,
            "maximo_movel_12_meses": 5.4883,
            "aceleracao_variacao_mensal": 0.08959
        },
        {
            "data": "2024-04-30",
            "valor": 5.4794,
            "variacao_absoluta_1_mes": 0.0729,
            "variacao_absoluta_3_meses": 0.119,
            "variacao_absoluta_12_meses": -0.0089,
            "variacao_1_mes_pct": 1.348377,
            "variacao_3_meses_pct": 2.219984,
            "variacao_6_meses_pct": 2.347909,
            "variacao_12_meses_pct": -0.162163,
            "media_movel_3": 5.4223,
            "media_movel_6": 5.38885,
            "media_movel_12": 5.348675,
            "desvio_media_movel_3_pct": 1.053059,
            "desvio_media_movel_12_pct": 2.444063,
            "volatilidade_12_meses": 1.320596,
            "minimo_movel_12_meses": 5.1895,
            "maximo_movel_12_meses": 5.4794,
            "aceleracao_variacao_mensal": 0.874487
        },
        {
            "data": "2024-05-31",
            "valor": 5.6311,
            "variacao_absoluta_1_mes": 0.1517,
            "variacao_absoluta_3_meses": 0.2501,
            "variacao_absoluta_12_meses": 0.2299,
            "variacao_1_mes_pct": 2.768551,
            "variacao_3_meses_pct": 4.647835,
            "variacao_6_meses_pct": 5.002984,
            "variacao_12_meses_pct": 4.256462,
            "media_movel_3": 5.505667,
            "media_movel_6": 5.433567,
            "media_movel_12": 5.367833,
            "desvio_media_movel_3_pct": 2.278259,
            "desvio_media_movel_12_pct": 4.904524,
            "volatilidade_12_meses": 1.439606,
            "minimo_movel_12_meses": 5.1895,
            "maximo_movel_12_meses": 5.6311,
            "aceleracao_variacao_mensal": 1.420174
        },
        {
            "data": "2024-06-30",
            "valor": 5.8909,
            "variacao_absoluta_1_mes": 0.2598,
            "variacao_absoluta_3_meses": 0.4844,
            "variacao_absoluta_12_meses": 0.617,
            "variacao_1_mes_pct": 4.613663,
            "variacao_3_meses_pct": 8.959586,
            "variacao_6_meses_pct": 10.254539,
            "variacao_12_meses_pct": 11.699122,
            "media_movel_3": 5.667133,
            "media_movel_6": 5.524883,
            "media_movel_12": 5.41925,
            "desvio_media_movel_3_pct": 3.948498,
            "desvio_media_movel_12_pct": 8.703234,
            "volatilidade_12_meses": 1.637511,
            "minimo_movel_12_meses": 5.1895,
            "maximo_movel_12_meses": 5.8909,
            "aceleracao_variacao_mensal": 1.845112
        },
        {
            "data": "2024-07-31",
            "valor": 6.0695,
            "variacao_absoluta_1_mes": 0.1786,
            "variacao_absoluta_3_meses": 0.5901,
            "variacao_absoluta_12_meses": 0.88,
            "variacao_1_mes_pct": 3.031795,
            "variacao_3_meses_pct": 10.769427,
            "variacao_6_meses_pct": 13.22849,
            "variacao_12_meses_pct": 16.957318,
            "media_movel_3": 5.863833,
            "media_movel_6": 5.643067,
            "media_movel_12": 5.492583,
            "desvio_media_movel_3_pct": 3.507376,
            "desvio_media_movel_12_pct": 10.503558,
            "volatilidade_12_meses": 1.526899,
            "minimo_movel_12_meses": 5.313,
            "maximo_movel_12_meses": 6.0695,
            "aceleracao_variacao_mensal": -1.581869
        },
        {
            "data": "2024-08-31",
            "valor": 6.2224,
            "variacao_absoluta_1_mes": 0.1529,
            "variacao_absoluta_3_meses": 0.5913,
            "variacao_absoluta_12_meses": 0.9094,
            "variacao_1_mes_pct": 2.519153,
            "variacao_3_meses_pct": 10.500613,
            "variacao_6_meses_pct": 15.636499,
            "variacao_12_meses_pct": 17.116507,
            "media_movel_3": 6.060933,
            "media_movel_6": 5.7833,
            "media_movel_12": 5.568367,
            "desvio_media_movel_3_pct": 2.664056,
            "desvio_media_movel_12_pct": 11.745515,
            "volatilidade_12_meses": 1.536158,
            "minimo_movel_12_meses": 5.3197,
            "maximo_movel_12_meses": 6.2224,
            "aceleracao_variacao_mensal": -0.512642
        },
        {
            "data": "2024-09-30",
            "valor": 6.0652,
            "variacao_absoluta_1_mes": -0.1572,
            "variacao_absoluta_3_meses": 0.1743,
            "variacao_absoluta_12_meses": 0.7455,
            "variacao_1_mes_pct": -2.526356,
            "variacao_3_meses_pct": 2.958801,
            "variacao_6_meses_pct": 12.183483,
            "variacao_12_meses_pct": 14.013948,
            "media_movel_3": 6.119033,
            "media_movel_6": 5.893083,
            "media_movel_12": 5.630492,
            "desvio_media_movel_3_pct": -0.879769,
            "desvio_media_movel_12_pct": 7.720611,
            "volatilidade_12_meses": 1.878708,
            "minimo_movel_12_meses": 5.343,
            "maximo_movel_12_meses": 6.2224,
            "aceleracao_variacao_mensal": -5.04551
        },
        {
            "data": "2024-10-31",
            "valor": 6.2522,
            "variacao_absoluta_1_mes": 0.187,
            "variacao_absoluta_3_meses": 0.1827,
            "variacao_absoluta_12_meses": 0.8985,
            "variacao_1_mes_pct": 3.083163,
            "variacao_3_meses_pct": 3.010133,
            "variacao_6_meses_pct": 14.103734,
            "variacao_12_meses_pct": 16.782786,
            "media_movel_3": 6.179933,
            "media_movel_6": 6.021883,
            "media_movel_12": 5.705367,
            "desvio_media_movel_3_pct": 1.169376,
            "desvio_media_movel_12_pct": 9.584543,
            "volatilidade_12_meses": 1.953432,
            "minimo_movel_12_meses": 5.343,
            "maximo_movel_12_meses": 6.2522,
            "aceleracao_variacao_mensal": 5.609519
        },
        {
            "data": "2024-11-30",
            "valor": 6.345178,
            "variacao_absoluta_1_mes": 0.092978,
            "variacao_absoluta_3_meses": 0.122778,
            "variacao_absoluta_12_meses": 0.982378,
            "variacao_1_mes_pct": 1.487125,
            "variacao_3_meses_pct": 1.973161,
            "variacao_6_meses_pct": 12.680968,
            "variacao_12_meses_pct": 18.318378,
            "media_movel_3": 6.220859,
            "media_movel_6": 6.140896,
            "media_movel_12": 5.787232,
            "desvio_media_movel_3_pct": 1.998416,
            "desvio_media_movel_12_pct": 9.640992,
            "volatilidade_12_meses": 1.919739,
            "minimo_movel_12_meses": 5.343,
            "maximo_movel_12_meses": 6.345178,
            "aceleracao_variacao_mensal": -1.596038
        },
        {
            "data": "2024-12-31",
            "valor": 6.422608,
            "variacao_absoluta_1_mes": 0.07743,
            "variacao_absoluta_3_meses": 0.357408,
            "variacao_absoluta_12_meses": 1.079608,
            "variacao_1_mes_pct": 1.220297,
            "variacao_3_meses_pct": 5.892765,
            "variacao_6_meses_pct": 9.025921,
            "variacao_12_meses_pct": 20.206027,
            "media_movel_3": 6.339995,
            "media_movel_6": 6.229514,
            "media_movel_12": 5.877199,
            "desvio_media_movel_3_pct": 1.30304,
            "desvio_media_movel_12_pct": 9.280087,
            "volatilidade_12_meses": 1.837512,
            "minimo_movel_12_meses": 5.3604,
            "maximo_movel_12_meses": 6.422608,
            "aceleracao_variacao_mensal": -0.266828
        },
        {
            "data": "2025-01-31",
            "valor": 6.101281,
            "variacao_absoluta_1_mes": -0.321327,
            "variacao_absoluta_3_meses": -0.150919,
            "variacao_absoluta_12_meses": 0.740881,
            "variacao_1_mes_pct": -5.003061,
            "variacao_3_meses_pct": -2.413854,
            "variacao_6_meses_pct": 0.523618,
            "variacao_12_meses_pct": 13.821375,
            "media_movel_3": 6.289689,
            "media_movel_6": 6.234811,
            "media_movel_12": 5.938939,
            "desvio_media_movel_3_pct": -2.995506,
            "desvio_media_movel_12_pct": 2.73352,
            "volatilidade_12_meses": 2.634274,
            "minimo_movel_12_meses": 5.381,
            "maximo_movel_12_meses": 6.422608,
            "aceleracao_variacao_mensal": -6.223358
        },
        {
            "data": "2025-02-28",
            "valor": 6.064281,
            "variacao_absoluta_1_mes": -0.037,
            "variacao_absoluta_3_meses": -0.280897,
            "variacao_absoluta_12_meses": 0.683281,
            "variacao_1_mes_pct": -0.60643,
            "variacao_3_meses_pct": -4.426936,
            "variacao_6_meses_pct": -2.541126,
            "variacao_12_meses_pct": 12.69803,
            "media_movel_3": 6.196057,
            "media_movel_6": 6.208458,
            "media_movel_12": 5.995879,
            "desvio_media_movel_3_pct": -2.126767,
            "desvio_media_movel_12_pct": 1.140817,
            "volatilidade_12_meses": 2.674534,
            "minimo_movel_12_meses": 5.4065,
            "maximo_movel_12_meses": 6.422608,
            "aceleracao_variacao_mensal": 4.396631
        },
        {
            "data": "2025-03-31",
            "valor": 6.22665,
            "variacao_absoluta_1_mes": 0.162369,
            "variacao_absoluta_3_meses": -0.195958,
            "variacao_absoluta_12_meses": 0.82015,
            "variacao_1_mes_pct": 2.677465,
            "variacao_3_meses_pct": -3.051066,
            "variacao_6_meses_pct": 2.661907,
            "variacao_12_meses_pct": 15.169703,
            "media_movel_3": 6.130737,
            "media_movel_6": 6.235366,
            "media_movel_12": 6.064225,
            "desvio_media_movel_3_pct": 1.564456,
            "desvio_media_movel_12_pct": 2.678416,
            "volatilidade_12_meses": 2.708006,
            "minimo_movel_12_meses": 5.4794,
            "maximo_movel_12_meses": 6.422608,
            "aceleracao_variacao_mensal": 3.283895
        },
        {
            "data": "2025-04-30",
            "valor": 6.393862,
            "variacao_absoluta_1_mes": 0.167212,
            "variacao_absoluta_3_meses": 0.292581,
            "variacao_absoluta_12_meses": 0.914462,
            "variacao_1_mes_pct": 2.685425,
            "variacao_3_meses_pct": 4.795403,
            "variacao_6_meses_pct": 2.265794,
            "variacao_12_meses_pct": 16.68909,
            "media_movel_3": 6.228264,
            "media_movel_6": 6.258977,
            "media_movel_12": 6.14043,
            "desvio_media_movel_3_pct": 2.658809,
            "desvio_media_movel_12_pct": 4.127268,
            "volatilidade_12_meses": 2.741169,
            "minimo_movel_12_meses": 5.6311,
            "maximo_movel_12_meses": 6.422608,
            "aceleracao_variacao_mensal": 0.00796
        },
        {
            "data": "2025-05-31",
            "valor": 6.43915,
            "variacao_absoluta_1_mes": 0.045288,
            "variacao_absoluta_3_meses": 0.374869,
            "variacao_absoluta_12_meses": 0.80805,
            "variacao_1_mes_pct": 0.708304,
            "variacao_3_meses_pct": 6.18159,
            "variacao_6_meses_pct": 1.480999,
            "variacao_12_meses_pct": 14.349772,
            "media_movel_3": 6.353221,
            "media_movel_6": 6.274639,
            "media_movel_12": 6.207768,
            "desvio_media_movel_3_pct": 1.352532,
            "desvio_media_movel_12_pct": 3.727306,
            "volatilidade_12_meses": 2.707134,
            "minimo_movel_12_meses": 5.8909,
            "maximo_movel_12_meses": 6.43915,
            "aceleracao_variacao_mensal": -1.97712
        },
        {
            "data": "2025-06-30",
            "valor": 6.418485,
            "variacao_absoluta_1_mes": -0.020665,
            "variacao_absoluta_3_meses": 0.191835,
            "variacao_absoluta_12_meses": 0.527585,
            "variacao_1_mes_pct": -0.320927,
            "variacao_3_meses_pct": 3.08087,
            "variacao_6_meses_pct": -0.064195,
            "variacao_12_meses_pct": 8.955932,
            "media_movel_3": 6.417166,
            "media_movel_6": 6.273952,
            "media_movel_12": 6.251733,
            "desvio_media_movel_3_pct": 0.020559,
            "desvio_media_movel_12_pct": 2.667294,
            "volatilidade_12_meses": 2.501386,
            "minimo_movel_12_meses": 6.064281,
            "maximo_movel_12_meses": 6.43915,
            "aceleracao_variacao_mensal": -1.029232
        },
        {
            "data": "2025-07-31",
            "valor": 6.365372,
            "variacao_absoluta_1_mes": -0.053113,
            "variacao_absoluta_3_meses": -0.02849,
            "variacao_absoluta_12_meses": 0.295872,
            "variacao_1_mes_pct": -0.827501,
            "variacao_3_meses_pct": -0.445584,
            "variacao_6_meses_pct": 4.328452,
            "variacao_12_meses_pct": 4.874734,
            "media_movel_3": 6.407669,
            "media_movel_6": 6.317967,
            "media_movel_12": 6.276389,
            "desvio_media_movel_3_pct": -0.6601,
            "desvio_media_movel_12_pct": 1.417743,
            "volatilidade_12_meses": 2.427843,
            "minimo_movel_12_meses": 6.064281,
            "maximo_movel_12_meses": 6.43915,
            "aceleracao_variacao_mensal": -0.506573
        },
        {
            "data": "2025-08-31",
            "valor": 6.317119,
            "variacao_absoluta_1_mes": -0.048253,
            "variacao_absoluta_3_meses": -0.122031,
            "variacao_absoluta_12_meses": 0.094719,
            "variacao_1_mes_pct": -0.758055,
            "variacao_3_meses_pct": -1.895141,
            "variacao_6_meses_pct": 4.169299,
            "variacao_12_meses_pct": 1.522226,
            "media_movel_3": 6.366992,
            "media_movel_6": 6.360106,
            "media_movel_12": 6.284282,
            "desvio_media_movel_3_pct": -0.783306,
            "desvio_media_movel_12_pct": 0.522523,
            "volatilidade_12_meses": 2.354029,
            "minimo_movel_12_meses": 6.064281,
            "maximo_movel_12_meses": 6.43915,
            "aceleracao_variacao_mensal": 0.069446
        },
        {
            "data": "2025-09-30",
            "valor": 6.238303,
            "variacao_absoluta_1_mes": -0.078816,
            "variacao_absoluta_3_meses": -0.180182,
            "variacao_absoluta_12_meses": 0.173103,
            "variacao_1_mes_pct": -1.247657,
            "variacao_3_meses_pct": -2.807236,
            "variacao_6_meses_pct": 0.187147,
            "variacao_12_meses_pct": 2.854036,
            "media_movel_3": 6.306931,
            "media_movel_6": 6.362048,
            "media_movel_12": 6.298707,
            "desvio_media_movel_3_pct": -1.088141,
            "desvio_media_movel_12_pct": -0.958997,
            "volatilidade_12_meses": 2.248355,
            "minimo_movel_12_meses": 6.064281,
            "maximo_movel_12_meses": 6.43915,
            "aceleracao_variacao_mensal": -0.489603
        },
        {
            "data": "2025-10-31",
            "valor": 6.222775,
            "variacao_absoluta_1_mes": -0.015528,
            "variacao_absoluta_3_meses": -0.142597,
            "variacao_absoluta_12_meses": -0.029425,
            "variacao_1_mes_pct": -0.248914,
            "variacao_3_meses_pct": -2.240199,
            "variacao_6_meses_pct": -2.675801,
            "variacao_12_meses_pct": -0.470634,
            "media_movel_3": 6.259399,
            "media_movel_6": 6.333534,
            "media_movel_12": 6.296255,
            "desvio_media_movel_3_pct": -0.585104,
            "desvio_media_movel_12_pct": -1.167048,
            "volatilidade_12_meses": 2.066123,
            "minimo_movel_12_meses": 6.064281,
            "maximo_movel_12_meses": 6.43915,
            "aceleracao_variacao_mensal": 0.998744
        },
        {
            "data": "2025-11-30",
            "valor": 6.207325,
            "variacao_absoluta_1_mes": -0.01545,
            "variacao_absoluta_3_meses": -0.109794,
            "variacao_absoluta_12_meses": -0.137853,
            "variacao_1_mes_pct": -0.248282,
            "variacao_3_meses_pct": -1.738039,
            "variacao_6_meses_pct": -3.600242,
            "variacao_12_meses_pct": -2.172563,
            "media_movel_3": 6.222801,
            "media_movel_6": 6.294896,
            "media_movel_12": 6.284768,
            "desvio_media_movel_3_pct": -0.248698,
            "desvio_media_movel_12_pct": -1.232227,
            "volatilidade_12_meses": 2.011082,
            "minimo_movel_12_meses": 6.064281,
            "maximo_movel_12_meses": 6.43915,
            "aceleracao_variacao_mensal": 0.000632
        },
        {
            "data": "2025-12-31",
            "valor": 6.426735,
            "variacao_absoluta_1_mes": 0.21941,
            "variacao_absoluta_3_meses": 0.188432,
            "variacao_absoluta_12_meses": 0.004127,
            "variacao_1_mes_pct": 3.534695,
            "variacao_3_meses_pct": 3.020565,
            "variacao_6_meses_pct": 0.128535,
            "variacao_12_meses_pct": 0.064257,
            "media_movel_3": 6.285612,
            "media_movel_6": 6.296272,
            "media_movel_12": 6.285111,
            "desvio_media_movel_3_pct": 2.245181,
            "desvio_media_movel_12_pct": 2.253317,
            "volatilidade_12_meses": 2.252417,
            "minimo_movel_12_meses": 6.064281,
            "maximo_movel_12_meses": 6.43915,
            "aceleracao_variacao_mensal": 3.782976
        },
        {
            "data": "2026-01-31",
            "valor": 6.203474,
            "variacao_absoluta_1_mes": -0.223261,
            "variacao_absoluta_3_meses": -0.019301,
            "variacao_absoluta_12_meses": 0.102193,
            "variacao_1_mes_pct": -3.473941,
            "variacao_3_meses_pct": -0.310167,
            "variacao_6_meses_pct": -2.543418,
            "variacao_12_meses_pct": 1.674943,
            "media_movel_3": 6.279178,
            "media_movel_6": 6.269289,
            "media_movel_12": 6.293628,
            "desvio_media_movel_3_pct": -1.205636,
            "desvio_media_movel_12_pct": -1.432458,
            "volatilidade_12_meses": 1.967048,
            "minimo_movel_12_meses": 6.064281,
            "maximo_movel_12_meses": 6.43915,
            "aceleracao_variacao_mensal": -7.008636
        },
        {
            "data": "2026-02-28",
            "valor": 6.056935,
            "variacao_absoluta_1_mes": -0.146539,
            "variacao_absoluta_3_meses": -0.15039,
            "variacao_absoluta_12_meses": -0.007346,
            "variacao_1_mes_pct": -2.362209,
            "variacao_3_meses_pct": -2.422783,
            "variacao_6_meses_pct": -4.118713,
            "variacao_12_meses_pct": -0.121136,
            "media_movel_3": 6.229048,
            "media_movel_6": 6.225925,
            "media_movel_12": 6.293015,
            "desvio_media_movel_3_pct": -2.763071,
            "desvio_media_movel_12_pct": -3.751467,
            "volatilidade_12_meses": 2.090365,
            "minimo_movel_12_meses": 6.056935,
            "maximo_movel_12_meses": 6.43915,
            "aceleracao_variacao_mensal": 1.111733
        },
        {
            "data": "2026-03-31",
            "valor": 6.027728,
            "variacao_absoluta_1_mes": -0.029207,
            "variacao_absoluta_3_meses": -0.399007,
            "variacao_absoluta_12_meses": -0.198922,
            "variacao_1_mes_pct": -0.482208,
            "variacao_3_meses_pct": -6.208549,
            "variacao_6_meses_pct": -3.375517,
            "variacao_12_meses_pct": -3.194687,
            "media_movel_3": 6.096046,
            "media_movel_6": 6.190829,
            "media_movel_12": 6.276439,
            "desvio_media_movel_3_pct": -1.120688,
            "desvio_media_movel_12_pct": -3.962607,
            "volatilidade_12_meses": 1.915486,
            "minimo_movel_12_meses": 6.027728,
            "maximo_movel_12_meses": 6.43915,
            "aceleracao_variacao_mensal": 1.880001
        },
        {
            "data": "2026-04-30",
            "valor": 5.858231,
            "variacao_absoluta_1_mes": -0.169497,
            "variacao_absoluta_3_meses": -0.345243,
            "variacao_absoluta_12_meses": -0.535631,
            "variacao_1_mes_pct": -2.811955,
            "variacao_3_meses_pct": -5.565317,
            "variacao_6_meses_pct": -5.858222,
            "variacao_12_meses_pct": -8.377269,
            "media_movel_3": 5.980965,
            "media_movel_6": 6.130071,
            "media_movel_12": 6.231803,
            "desvio_media_movel_3_pct": -2.052071,
            "desvio_media_movel_12_pct": -5.9946,
            "volatilidade_12_meses": 1.802791,
            "minimo_movel_12_meses": 5.858231,
            "maximo_movel_12_meses": 6.43915,
            "aceleracao_variacao_mensal": -2.329747
        },
        {
            "data": "2026-05-31",
            "valor": 5.882353,
            "variacao_absoluta_1_mes": 0.024122,
            "variacao_absoluta_3_meses": -0.174582,
            "variacao_absoluta_12_meses": -0.556797,
            "variacao_1_mes_pct": 0.411763,
            "variacao_3_meses_pct": -2.882349,
            "variacao_6_meses_pct": -5.235299,
            "variacao_12_meses_pct": -8.647057,
            "media_movel_3": 5.922771,
            "media_movel_6": 6.075909,
            "media_movel_12": 6.185403,
            "desvio_media_movel_3_pct": -0.682411,
            "desvio_media_movel_12_pct": -4.899437,
            "volatilidade_12_meses": 1.783488,
            "minimo_movel_12_meses": 5.858231,
            "maximo_movel_12_meses": 6.426735,
            "aceleracao_variacao_mensal": 3.223718
        },
        {
            "data": "2026-06-30",
            "valor": 5.91716,
            "variacao_absoluta_1_mes": 0.034807,
            "variacao_absoluta_3_meses": -0.110568,
            "variacao_absoluta_12_meses": -0.501325,
            "variacao_1_mes_pct": 0.591719,
            "variacao_3_meses_pct": -1.834323,
            "variacao_6_meses_pct": -7.928987,
            "variacao_12_meses_pct": -7.810644,
            "media_movel_3": 5.885915,
            "media_movel_6": 5.99098,
            "media_movel_12": 6.143626,
            "desvio_media_movel_3_pct": 0.530849,
            "desvio_media_movel_12_pct": -3.686192,
            "volatilidade_12_meses": 1.821856,
            "minimo_movel_12_meses": 5.858231,
            "maximo_movel_12_meses": 6.426735,
            "aceleracao_variacao_mensal": 0.179956
        },
        {
            "data": "2026-07-31",
            "valor": 5.7601,
            "variacao_absoluta_1_mes": -0.15706,
            "variacao_absoluta_3_meses": -0.098131,
            "variacao_absoluta_12_meses": -0.605272,
            "variacao_1_mes_pct": -2.654314,
            "variacao_3_meses_pct": -1.675096,
            "variacao_6_meses_pct": -7.147189,
            "variacao_12_meses_pct": -9.508824,
            "media_movel_3": 5.853204,
            "media_movel_6": 5.917085,
            "media_movel_12": 6.093187,
            "desvio_media_movel_3_pct": -1.590656,
            "desvio_media_movel_12_pct": -5.46654,
            "volatilidade_12_meses": 1.911237,
            "minimo_movel_12_meses": 5.7601,
            "maximo_movel_12_meses": 6.426735,
            "aceleracao_variacao_mensal": -3.246033
        }
    ]
}